subbreaker/__init__.py
subbreaker/breaker.py
subbreaker/command.py
subbreaker/key.py
subbreaker/quadgram/EN.json
subbreaker-1.2.0.dist-info/LICENSE
subbreaker-1.2.0.dist-info/METADATA
subbreaker-1.2.0.dist-info/WHEEL
subbreaker-1.2.0.dist-info/entry_points.txt
subbreaker-1.2.0.dist-info/top_level.txt
subbreaker-1.2.0.dist-info/zip-safe
subbreaker-1.2.0.dist-info/RECORD
