Metadata-Version: 2.1
Name: subbreaker
Version: 1.2.0
Summary: A tool to break substitution ciphers
Home-page: https://gitlab.com/guballa/SubstitutionBreaker
Author: Jens Guballa
Author-email: jens@guballa.de
License: MIT
Project-URL: Bug Tracker, https://gitlab.com/guballa/SubstitutionBreaker/issues
Project-URL: Changelog, https://gitlab.com/guballa/SubstitutionBreaker/-/blob/master/CHANGELOG.rst
Project-URL: Source, https://gitlab.com/guballa/SubstitutionBreaker
Keywords: classical cipher breaker solver substitution cryptogram
Platform: any
Classifier: Development Status :: 5 - Production/Stable
Classifier: Intended Audience :: Developers
Classifier: License :: OSI Approved :: MIT License
Classifier: Operating System :: OS Independent
Classifier: Programming Language :: Python
Classifier: Programming Language :: Python :: 3.5
Classifier: Programming Language :: Python :: 3.6
Classifier: Programming Language :: Python :: 3.7
Classifier: Programming Language :: Python :: 3.8
Classifier: Topic :: Software Development :: Libraries :: Python Modules
Requires-Python: <4,>=3.5
Requires-Dist: importlib-metadata ; python_version < "3.8"
Provides-Extra: dev
Requires-Dist: pytest ; extra == 'dev'
Requires-Dist: pytest-cov ; extra == 'dev'
Requires-Dist: black ; extra == 'dev'
Requires-Dist: flake8 ; extra == 'dev'
Requires-Dist: sphinx ; extra == 'dev'
Requires-Dist: sphinx-argparse ; extra == 'dev'
Requires-Dist: tox ; extra == 'dev'
Requires-Dist: sphinx-rtd-theme ; extra == 'dev'
